[
  {
    "in": true,
    "n": "iOS13.2",
    "u": "/Fonts/Emoji/iOS13.2.ttf",
    "s": "42.1 MB",
    "t": "jlfUZxQ.png"
  },
  {
    "n": "iOS10.2",
    "u": "/Fonts/Emoji/iOS10.2.ttf",
    "in": true,
    "s": "41.2 MB",
    "t": "hyLk7LD.png"
  },
  {
    "n": "IOS12.1",
    "u": "/Fonts/Emoji/iOS12.1.ttf",
    "in": true,
    "s": "24.8 MB",
    "t": "4jssrGb.png"
  },
  {
    "n": "iOS12",
    "u": "/Fonts/Emoji/iOS12.ttf",
    "s": "17.1 MB",
    "t": "0n0KZgn.png"
  },
  {
    "n": "iOS 11",
    "s": "22.08 MB",
    "u": "/Fonts/Emoji/iOS11Emoji.ttf",
    "t": "04inix4.png"
  },
  {
    "n": "Twemoji",
    "u": "/Fonts/Emoji/Twemoji.ttf",
    "s": "17.03 MB",
    "t": "QQD64wg.png"
  },
  {
    "n": "Windows 10",
    "u": "/Fonts/Emoji/Windows10Emoji.ttf",
    "s": "17.11 MB",
    "t": "RQGkAoF.png"
  },
  {
    "n": "Android P",
    "u": "/Fonts/Emoji/AndroidPEmoji.ttf",
    "s": "14.00 MB",
    "t": "DB6FF66.png"
  },
  {
    "n": "Facebook",
    "u": "/Fonts/Emoji/FacebookEmoji.ttf",
    "s": "12.06 MB",
    "t": "K01I4S2.png"
  },
  {
    "n": "Android L",
    "u": "/Fonts/Emoji/Android L.ttf",
    "s": "4.88 MB",
    "t": "qDJaeYq.png"
  },
  {
    "n": "HTC Sense",
    "u": "/Fonts/Emoji/HTC Sense.ttf",
    "s": "5.09 MB",
    "t": "MIAULCs.png"
  },
  {
    "n": "iOS",
    "u": "/Fonts/Emoji/iOS.ttf",
    "s": "6.44 MB",
    "t": "Ue3eQf4.png"
  },
  {
    "n": "LG",
    "u": "/Fonts/Emoji/LG.ttf",
    "s": "6.15 MB",
    "t": "UchUgiv.png"
  },
  {
    "n": "Phantom",
    "u": "/Fonts/Emoji/Phantom.ttf",
    "s": "702 KB",
    "t": "dfZ1Mbu.png"
  },
  {
    "n": "Pixels",
    "u": "/Fonts/Emoji/Pixels.ttf",
    "s": "1.90 MB",
    "t": "X1VdjH6.png"
  },
  {
    "n": "Samsung",
    "u": "/Fonts/Emoji/Samsung.ttf",
    "s": "6.48 MB",
    "t": "YzK9XOs.png"
  },
  {
    "n": "Twitter",
    "u": "/Fonts/Emoji/Twitter.ttf",
    "s": "2.53 MB",
    "t": "8VgEvLV.png"
  },
  {
    "n": "Unknown",
    "u": "/Fonts/Emoji/Unknown.ttf",
    "s": "2.93 MB",
    "t": "MBEIAuV.png"
  },
  {
    "n": "SamsungPie",
    "u": "/Fonts/Emoji/SamsungPie.ttf",
    "s": "10.6 MB",
    "t": "lf4NH4A.png"
  }
]
